nonebot_plugin_ernie/__init__.py
nonebot_plugin_ernie/config.py
nonebot_plugin_ernie/utils.py
nonebot_plugin_ernie-1.1.0.dist-info/LICENSE
nonebot_plugin_ernie-1.1.0.dist-info/METADATA
nonebot_plugin_ernie-1.1.0.dist-info/WHEEL
nonebot_plugin_ernie-1.1.0.dist-info/RECORD
