Metadata-Version: 2.3
Name: nonebot-plugin-ernie
Version: 1.1.0
Summary: 文心一言 Nonebot 插件
License: MIT
Author: Noctulus
Author-email: fangyuhao0612@gmail.com
Requires-Python: >=3.10,<4
Classifier: License :: OSI Approved :: MIT License
Classifier: Programming Language :: Python :: 3
Classifier: Programming Language :: Python :: 3.10
Classifier: Programming Language :: Python :: 3.11
Classifier: Programming Language :: Python :: 3.12
Classifier: Programming Language :: Python :: 3.13
Requires-Dist: httpx (>=0.19.0)
Requires-Dist: nonebot-plugin-alconna (>=0.57.4,<0.58.0)
Requires-Dist: nonebot-plugin-apscheduler (>=0.5.0,<0.6.0)
Requires-Dist: nonebot-plugin-htmlrender (>=0.5.0)
Requires-Dist: nonebot2 (>=2.1.2)
Project-URL: Homepage, https://github.com/Noctulus/nonebot-plugin-ernie
